aicssegmentation/__init__.py
aicssegmentation/exceptions.py
aicssegmentation/assets/diagrams/actb.png
aicssegmentation/assets/diagrams/actn1.png
aicssegmentation/assets/diagrams/atp2a2.png
aicssegmentation/assets/diagrams/cetn2.png
aicssegmentation/assets/diagrams/ctnnb1.png
aicssegmentation/assets/diagrams/dsp.png
aicssegmentation/assets/diagrams/fbl.png
aicssegmentation/assets/diagrams/gja1.png
aicssegmentation/assets/diagrams/h2b_interphase.png
aicssegmentation/assets/diagrams/lamp1.png
aicssegmentation/assets/diagrams/lmnb1_interphase.png
aicssegmentation/assets/diagrams/lmnb1_mitotic.png
aicssegmentation/assets/diagrams/myh10.png
aicssegmentation/assets/diagrams/npm1.png
aicssegmentation/assets/diagrams/nup153.png
aicssegmentation/assets/diagrams/pxn.png
aicssegmentation/assets/diagrams/rab5a.png
aicssegmentation/assets/diagrams/sec61b.png
aicssegmentation/assets/diagrams/slc25a17.png
aicssegmentation/assets/diagrams/smc1a.png
aicssegmentation/assets/diagrams/son.png
aicssegmentation/assets/diagrams/st6gal1.png
aicssegmentation/assets/diagrams/tjp1.png
aicssegmentation/assets/diagrams/tomm20.png
aicssegmentation/assets/diagrams/tuba1b.png
aicssegmentation/assets/thumbnails/actb_post.png
aicssegmentation/assets/thumbnails/actb_pre.png
aicssegmentation/assets/thumbnails/actn1_post.png
aicssegmentation/assets/thumbnails/actn1_pre.png
aicssegmentation/assets/thumbnails/atp2a2_post.png
aicssegmentation/assets/thumbnails/atp2a2_pre.png
aicssegmentation/assets/thumbnails/cetn2_post.png
aicssegmentation/assets/thumbnails/cetn2_pre.png
aicssegmentation/assets/thumbnails/ctnnb1_post.png
aicssegmentation/assets/thumbnails/ctnnb1_pre.png
aicssegmentation/assets/thumbnails/dsp_post.png
aicssegmentation/assets/thumbnails/dsp_pre.png
aicssegmentation/assets/thumbnails/fbl_post.png
aicssegmentation/assets/thumbnails/fbl_pre.png
aicssegmentation/assets/thumbnails/gja1_post.png
aicssegmentation/assets/thumbnails/gja1_pre.png
aicssegmentation-0.5.3.dist-info/LICENSE
aicssegmentation-0.5.3.dist-info/METADATA
aicssegmentation-0.5.3.dist-info/WHEEL
aicssegmentation-0.5.3.dist-info/entry_points.txt
aicssegmentation-0.5.3.dist-info/top_level.txt
aicssegmentation-0.5.3.dist-info/RECORD
